FlickrMirroring/__init__.py
FlickrMirroring/__main__.py
FlickrMirroring/model/FlickrApi.py
FlickrMirroring/model/FlickrPhoto.py
FlickrMirroring/model/FlickrPhotoSize.py
FlickrMirroring/model/FlickrUser.py
FlickrMirroring/model/Label.py
FlickrMirroring/model/Locale.py
FlickrMirroring/model/__init__.py
FlickrMirroring/model/constants.py
FlickrMirroring-1.0.1.dist-info/LICENSE
FlickrMirroring-1.0.1.dist-info/METADATA
FlickrMirroring-1.0.1.dist-info/WHEEL
FlickrMirroring-1.0.1.dist-info/entry_points.txt
FlickrMirroring-1.0.1.dist-info/top_level.txt
FlickrMirroring-1.0.1.dist-info/RECORD
