Metadata-Version: 2.1
Name: FlickrMirroring
Version: 1.0.1
Summary: A tool to mirror Flickr photo
Home-page: https://github.com/intek-training-jsc/flickr-mirroring-tcthai
Author: tcthai
Author-email: thai.tran@f4.intek.edu.vn
License: MIT
Platform: UNKNOWN
Classifier: License :: OSI Approved :: MIT License
Classifier: Programming Language :: Python :: 3
Classifier: Programming Language :: Python :: 3.6
Requires-Dist: httplib2
Requires-Dist: langdetect
Requires-Dist: iso-639
